README.md
setup.py
ATPL/UI_window.py
ATPL/__init__.py
ATPL.egg-info/PKG-INFO
ATPL.egg-info/SOURCES.txt
ATPL.egg-info/dependency_links.txt
ATPL.egg-info/requires.txt
ATPL.egg-info/top_level.txt
ATPL/common/__init__.py
ATPL/common/comFuction.py
ATPL/dylib/matchsig.dylib
ATPL/main_flow/__init__.py
ATPL/main_flow/main_flow.py
ATPL/src/speech.wav
ATPL/target/ATPL_run.py